vease_viewer/app.py
vease_viewer/py.typed
vease_viewer/rpc/protocols.py
vease_viewer/rpc/schemas/__init__.py
vease_viewer/rpc/schemas/microservice_version.json
vease_viewer/rpc/schemas/microservice_version.py
vease_viewer-2.4.1.dist-info/licenses/LICENSE
vease_viewer-2.4.1.dist-info/METADATA
vease_viewer-2.4.1.dist-info/WHEEL
vease_viewer-2.4.1.dist-info/entry_points.txt
vease_viewer-2.4.1.dist-info/top_level.txt
vease_viewer-2.4.1.dist-info/RECORD
